{
 "cards": [
  {
   "card": "Total Waiter"
  },
  {
   "card": "Total chefs"
  },
  {
   "card": "Total Orders Today"
  },
  {
   "card": "Total Main Course Item"
  },
  {
   "card": "Total Starter Item"
  },
  {
   "card": "Total Beverages Item"
  },
  {
   "card": "Reserved Tables"
  },
  {
   "card": "Occupied Tables"
  }
 ],
 "charts": [
  {
   "chart": "Daily Customer Count",
   "width": "Half"
  },
  {
   "chart": "Daily Sales Invoice Count",
   "width": "Half"
  }
 ],
 "creation": "2026-02-05 15:44:02.994277",
 "dashboard_name": "Info Board",
 "docstatus": 0,
 "doctype": "Dashboard",
 "idx": 1,
 "is_default": 0,
 "is_standard": 1,
 "modified": "2026-02-06 15:20:29.312934",
 "modified_by": "Administrator",
 "module": "Restaurant Management",
 "name": "Info Board",
 "owner": "Administrator"
}